setup.py
bnd_package/Binomialdistribution.py
bnd_package/Gaussiandistribution.py
bnd_package/Generaldistribution.py
bnd_package/__init__.py
bnd_package.egg-info/PKG-INFO
bnd_package.egg-info/SOURCES.txt
bnd_package.egg-info/dependency_links.txt
bnd_package.egg-info/not-zip-safe
bnd_package.egg-info/top_level.txt