Metadata-Version: 1.0
Name: bnd-package
Version: 0.1
Summary: Gaussian and binomial distributions
Home-page: UNKNOWN
Author: Gabriel Chiong
Author-email: my_name109@hotmail.com
License: UNKNOWN
Platform: UNKNOWN
